panasonic_viera/__init__.py
panasonic_viera/__main__.py
panasonic_viera-0.4.2.dist-info/LICENSE
panasonic_viera-0.4.2.dist-info/METADATA
panasonic_viera-0.4.2.dist-info/WHEEL
panasonic_viera-0.4.2.dist-info/RECORD
