Metadata-Version: 2.1
Name: panasonic-viera
Version: 0.4.2
Summary: Library to control Panasonic Viera TVs
License: MIT
Author: Florian Holzapfel
Author-email: flo.holzapfel@gmail.com
Requires-Python: >=3.8,<4.0
Classifier: License :: OSI Approved :: MIT License
Classifier: Programming Language :: Python :: 3
Classifier: Programming Language :: Python :: 3.8
Classifier: Programming Language :: Python :: 3.9
Classifier: Programming Language :: Python :: 3.10
Classifier: Programming Language :: Python :: 3.11
Classifier: Programming Language :: Python :: 3.12
Requires-Dist: aiohttp (>=3.9.5,<4.0.0)
Requires-Dist: pycryptodome (>=3.20.0,<4.0.0)
Requires-Dist: xmltodict (>=0.13.0,<0.14.0)
